examples/full.py
nucleus/__init__.py
nucleus/core/__init__.py
nucleus/core/constants.py
nucleus/core/dataclass.py
nucleus/core/decorators.py
nucleus/core/exceptions.py
nucleus/core/logger.py
nucleus/core/types.py
nucleus/core/blockchain/__init__.py
nucleus/core/blockchain/constants.py
nucleus/core/blockchain/crypto.py
nucleus/core/blockchain/types.py
nucleus/core/cache/__init__.py
nucleus/core/cache/constants.py
nucleus/core/cache/database.py
nucleus/core/cache/types.py
nucleus/core/http/__init__.py
nucleus/core/http/partials.py
nucleus/core/http/session.py
nucleus/core/http/types.py
nucleus/core/ipfs/__init__.py
nucleus/core/ipfs/connect.py
nucleus/core/ipfs/constants.py
nucleus/core/ipfs/rpc.py
nucleus/core/ipfs/types.py
nucleus/core/ipfs/cmd/__init__.py
nucleus/core/ipfs/cmd/add.py
nucleus/core/ipfs/cmd/block.py
nucleus/core/ipfs/cmd/constants.py
nucleus/core/ipfs/cmd/dag.py
nucleus/core/ipfs/cmd/inputs.py
nucleus/core/subprocess/__init__.py
nucleus/core/subprocess/constants.py
nucleus/core/subprocess/exec.py
nucleus/core/subprocess/ipc.py
nucleus/core/subprocess/protocol.py
nucleus/core/subprocess/types.py
nucleus/sdk/__init__.py
nucleus/sdk/exceptions.py
nucleus/sdk/expose/__init__.py
nucleus/sdk/expose/crypto.py
nucleus/sdk/expose/factory.py
nucleus/sdk/expose/key.py
nucleus/sdk/expose/marshall.py
nucleus/sdk/expose/metadata.py
nucleus/sdk/expose/sep.py
nucleus/sdk/expose/types.py
nucleus/sdk/harvest/__init__.py
nucleus/sdk/harvest/collectors.py
nucleus/sdk/harvest/constants.py
nucleus/sdk/harvest/media.py
nucleus/sdk/harvest/models.py
nucleus/sdk/harvest/partials.py
nucleus/sdk/harvest/types.py
nucleus/sdk/processing/__init__.py
nucleus/sdk/processing/engines.py
nucleus/sdk/processing/process.py
nucleus/sdk/processing/types.py
nucleus/sdk/processing/image/__init__.py
nucleus/sdk/processing/image/settings.py
nucleus/sdk/processing/video/__init__.py
nucleus/sdk/processing/video/codecs.py
nucleus/sdk/processing/video/constants.py
nucleus_sdk-0.1a5.dist-info/METADATA
nucleus_sdk-0.1a5.dist-info/WHEEL
nucleus_sdk-0.1a5.dist-info/licenses/LICENSE
nucleus_sdk-0.1a5.dist-info/RECORD
