Metadata-Version: 2.1
Name: nucleus-sdk
Version: 0.1a5
Summary: The building block for decentralized media
Project-URL: Bug Reports, https://github.com/SynapseMedia/nucleus/issues
Project-URL: Funding, https://opencollective.com/synapse
Project-URL: Homepage, https://github.com/SynapseMedia/nucleus
Project-URL: Source, https://opencollective.com/synapse
Author-email: Synapse <gmjun2000@gmail.com>
Maintainer-email: Geolffrey Mena <gmjun2000@gmail.com>
License:                     GNU AFFERO GENERAL PUBLIC LICENSE
License-File: LICENSE
Keywords: decentralization,development,media
Classifier: Development Status :: 3 - Alpha
Classifier: Intended Audience :: Developers
Classifier: Intended Audience :: Information Technology
Classifier: License :: OSI Approved :: GNU Affero General Public License v3 or later (AGPLv3+)
Classifier: Programming Language :: Python :: 3
Classifier: Programming Language :: Python :: 3 :: Only
Classifier: Programming Language :: Python :: 3.10
Classifier: Programming Language :: Python :: 3.11
Classifier: Topic :: Software Development :: Build Tools
Requires-Python: >=3.10
Requires-Dist: dag-cbor>=0.3.2
Requires-Dist: ffmpeg-python>=0.2.0
Requires-Dist: hexbytes>=0.2.2
Requires-Dist: jwcrypto>=1.4.2
Requires-Dist: multiformats>=0.2.1
Requires-Dist: pillow>=9.2.0
Requires-Dist: pydantic>=1.10.1
Requires-Dist: requests>=2.27.1
Requires-Dist: rich>=13.3.5
Requires-Dist: setuptools>=67.8.0
Requires-Dist: urllib3>=2.0.3
Requires-Dist: web3>=6.4.0
